Flickpy/__init__.py
Flickpy/animations.py
Flickpy/cli.py
flickpy-3.0.0.dist-info/METADATA
flickpy-3.0.0.dist-info/WHEEL
flickpy-3.0.0.dist-info/entry_points.txt
flickpy-3.0.0.dist-info/top_level.txt
flickpy-3.0.0.dist-info/RECORD
