Metadata-Version: 2.1
Name: flickpy
Version: 3.0.0
Summary: A Python package for displaying various loading animations in the terminal.
Home-page: https://github.com/bytebreach/flickpy
Author: MrFidal
Author-email: mrfidal@proton.me
Classifier: Programming Language :: Python :: 3
Classifier: License :: OSI Approved :: MIT License
Classifier: Operating System :: OS Independent
